{
  "generated_at": "2026-07-16T04:56:54.239730Z",
  "date_range": {
    "from": "2026-07-16",
    "to": "2026-07-16"
  },
  "resolution": "5",
  "legs": [
    {
      "name": "Leg1 - Sell 23900 PE",
      "symbol": "NSE:NIFTY2672124300CE",
      "side": "SELL",
      "lots": 15,
      "lot_size": 65,
      "entry_price": 59.27
    },
    {
      "name": "Leg2 - buy 23750 PE",
      "symbol": "NSE:NIFTY26JUL24300CE",
      "side": "BUY",
      "lots": 15,
      "lot_size": 65,
      "entry_price": 138.42
    }
  ],
  "timeseries": [
    {
      "ts": 1784173500,
      "legs": {
        "Leg1 - Sell 23900 PE": -13581.75,
        "Leg2 - buy 23750 PE": 10315.5
      },
      "total": -3266.25
    },
    {
      "ts": 1784173800,
      "legs": {
        "Leg1 - Sell 23900 PE": -8950.5,
        "Leg2 - buy 23750 PE": 7975.5
      },
      "total": -975.0
    },
    {
      "ts": 1784174100,
      "legs": {
        "Leg1 - Sell 23900 PE": -6269.25,
        "Leg2 - buy 23750 PE": 5343.0
      },
      "total": -926.25
    },
    {
      "ts": 1784174400,
      "legs": {
        "Leg1 - Sell 23900 PE": -663.0,
        "Leg2 - buy 23750 PE": -848.25
      },
      "total": -1511.25
    },
    {
      "ts": 1784174700,
      "legs": {
        "Leg1 - Sell 23900 PE": -614.25,
        "Leg2 - buy 23750 PE": -848.25
      },
      "total": -1462.5
    },
    {
      "ts": 1784175000,
      "legs": {
        "Leg1 - Sell 23900 PE": -6318.0,
        "Leg2 - buy 23750 PE": 5928.0
      },
      "total": -390.0
    },
    {
      "ts": 1784175300,
      "legs": {
        "Leg1 - Sell 23900 PE": -760.5,
        "Leg2 - buy 23750 PE": 78.0
      },
      "total": -682.5
    },
    {
      "ts": 1784175600,
      "legs": {
        "Leg1 - Sell 23900 PE": -2954.25,
        "Leg2 - buy 23750 PE": 1784.25
      },
      "total": -1170.0
    },
    {
      "ts": 1784175900,
      "legs": {
        "Leg1 - Sell 23900 PE": -2954.25,
        "Leg2 - buy 23750 PE": 3003.0
      },
      "total": 48.75
    },
    {
      "ts": 1784176200,
      "legs": {
        "Leg1 - Sell 23900 PE": -1833.0,
        "Leg2 - buy 23750 PE": 2125.5
      },
      "total": 292.5
    },
    {
      "ts": 1784176500,
      "legs": {
        "Leg1 - Sell 23900 PE": 68.25,
        "Leg2 - buy 23750 PE": -1189.5
      },
      "total": -1121.25
    },
    {
      "ts": 1784176800,
      "legs": {
        "Leg1 - Sell 23900 PE": -663.0,
        "Leg2 - buy 23750 PE": -68.25
      },
      "total": -731.25
    },
    {
      "ts": 1784177100,
      "legs": {
        "Leg1 - Sell 23900 PE": -468.0,
        "Leg2 - buy 23750 PE": 760.5
      },
      "total": 292.5
    },
    {
      "ts": 1784177400,
      "legs": {
        "Leg1 - Sell 23900 PE": -1053.0,
        "Leg2 - buy 23750 PE": 906.75
      },
      "total": -146.25
    },
    {
      "ts": 1784177700,
      "legs": {
        "Leg1 - Sell 23900 PE": 1482.0,
        "Leg2 - buy 23750 PE": -2359.5
      },
      "total": -877.5
    }
  ]
}